{"userProfileId": 116219307, "totalKilocalories": 2384.0, "activeKilocalories": 508.0, "bmrKilocalories": 1876.0, "wellnessKilocalories": 2384.0, "burnedKilocalories": null, "consumedKilocalories": null, "remainingKilocalories": 2384.0, "totalSteps": 15267, "netCalorieGoal": null, "totalDistanceMeters": 11941, "wellnessDistanceMeters": 11941, "wellnessActiveKilocalories": 508.0, "netRemainingKilocalories": 508.0, "userDailySummaryId": 116219307, "calendarDate": "2024-01-02", "rule": {"typeId": 2, "typeKey": "private"}, "uuid": "7c15b720c5ca4e70a12378bf0f64aa45", "dailyStepGoal": 10000, "wellnessStartTimeGmt": "2024-01-01T23:00:00.0", "wellnessStartTimeLocal": "2024-01-02T00:00:00.0", "wellnessEndTimeGmt": "2024-01-02T23:00:00.0", "wellnessEndTimeLocal": "2024-01-03T00:00:00.0", "durationInMilliseconds": 86400000, "wellnessDescription": null, "highlyActiveSeconds": 2998, "activeSeconds": 10805, "sedentarySeconds": 41697, "sleepingSeconds": 30900, "includesWellnessData": true, "includesActivityData": true, "includesCalorieConsumedData": false, "privacyProtected": false, "moderateIntensityMinutes": 9, "vigorousIntensityMinutes": 0, "floorsAscendedInMeters": 64.008, "floorsDescendedInMeters": 68.971, "floorsAscended": 21.0, "floorsDescended": 22.62828, "intensityMinutesGoal": 150, "userFloorsAscendedGoal": 10, "minHeartRate": 49, "maxHeartRate": 110, "restingHeartRate": 50, "lastSevenDaysAvgRestingHeartRate": 49, "source": "GARMIN", "averageStressLevel": 40, "maxStressLevel": 94, "stressDuration": 36840, "restStressDuration": 27780, "activityStressDuration": 15120, "uncategorizedStressDuration": 5760, "totalStressDuration": 85500, "lowStressDuration": 13320, "mediumStressDuration": 17280, "highStressDuration": 6240, "stressPercentage": 43.09, "restStressPercentage": 32.49, "activityStressPercentage": 17.68, "uncategorizedStressPercentage": 6.74, "lowStressPercentage": 15.58, "mediumStressPercentage": 20.21, "highStressPercentage": 7.3, "stressQualifier": "STRESSFUL", "measurableAwakeDuration": 49020, "measurableAsleepDuration": 30720, "lastSyncTimestampGMT": null, "minAvgHeartRate": 49, "maxAvgHeartRate": 107, "bodyBatteryChargedValue": 61, "bodyBatteryDrainedValue": 79, "bodyBatteryHighestValue": 83, "bodyBatteryLowestValue": 20, "bodyBatteryMostRecentValue": 27, "bodyBatteryDuringSleep": 47, "bodyBatteryVersion": 3.0, "abnormalHeartRateAlertsCount": null, "averageSpo2": null, "lowestSpo2": null, "latestSpo2": null, "latestSpo2ReadingTimeGmt": null, "latestSpo2ReadingTimeLocal": null, "averageMonitoringEnvironmentAltitude": 82.0, "restingCaloriesFromActivity": 13.0, "bodyBatteryDynamicFeedbackEvent": {"eventTimestampGmt": "2024-01-02T22:01:04", "bodyBatteryLevel": "MODERATE", "feedbackShortType": "SLEEP_PREPARATION_STRESSFUL_AND_EXERCISE", "feedbackLongType": "SLEEP_PREPARATION_STRESSFUL_AND_EXERCISE"}, "endOfDayBodyBatteryDynamicFeedbackEvent": {"eventTimestampGmt": "2024-01-02T22:30:15", "bodyBatteryLevel": "MODERATE", "feedbackShortType": "SLEEP_TIME_PASSED_STRESSFUL_AND_EXERCISE", "feedbackLongType": "SLEEP_TIME_PASSED_STRESSFUL_AND_EXERCISE"}, "bodyBatteryActivityEventList": [{"eventType": "SLEEP", "eventStartTimeGmt": "2024-01-02T02:56:00", "timezoneOffset": 3600000, "durationInMilliseconds": 24480000, "bodyBatteryImpact": 47, "feedbackType": "NONE", "shortFeedback": "NONE", "deviceId": 3446825437, "activityName": null, "activityType": null, "activityId": null, "eventUpdateTimeGmt": "2024-01-02T09:44:20"}, {"eventType": "ACTIVITY", "eventStartTimeGmt": "2024-01-02T18:48:33", "timezoneOffset": 3600000, "durationInMilliseconds": 1020000, "bodyBatteryImpact": -1, "feedbackType": "EXERCISE_TRAINING_EFFECT_BELOW_2", "shortFeedback": "NONE", "deviceId": 3446825437, "activityName": "Bochum Walking", "activityType": "walking", "activityId": 13391344475, "eventUpdateTimeGmt": "2024-01-02T19:06:06"}], "avgWakingRespirationValue": 14.0, "highestRespirationValue": 21.0, "lowestRespirationValue": 9.0, "latestRespirationValue": 14.0, "latestRespirationTimeGMT": "2024-01-02T23:00:00.0"}