{"userProfileId": 116219307, "totalKilocalories": 1880.0, "activeKilocalories": 4.0, "bmrKilocalories": 1876.0, "wellnessKilocalories": 1880.0, "burnedKilocalories": null, "consumedKilocalories": null, "remainingKilocalories": 1880.0, "totalSteps": 430, "netCalorieGoal": null, "totalDistanceMeters": 335, "wellnessDistanceMeters": 335, "wellnessActiveKilocalories": 4.0, "netRemainingKilocalories": 4.0, "userDailySummaryId": 116219307, "calendarDate": "2024-02-05", "rule": {"typeId": 2, "typeKey": "private"}, "uuid": "08ae814413eb48108598e70584f2ae74", "dailyStepGoal": 10000, "wellnessStartTimeGmt": "2024-02-04T23:00:00.0", "wellnessStartTimeLocal": "2024-02-05T00:00:00.0", "wellnessEndTimeGmt": "2024-02-05T23:00:00.0", "wellnessEndTimeLocal": "2024-02-06T00:00:00.0", "durationInMilliseconds": 86400000, "wellnessDescription": null, "highlyActiveSeconds": 171, "activeSeconds": 262, "sedentarySeconds": 53528, "sleepingSeconds": 32439, "includesWellnessData": true, "includesActivityData": false, "includesCalorieConsumedData": false, "privacyProtected": false, "moderateIntensityMinutes": 0, "vigorousIntensityMinutes": 0, "floorsAscendedInMeters": 3.048, "floorsDescendedInMeters": 2.367, "floorsAscended": 1.0, "floorsDescended": 0.77657, "intensityMinutesGoal": 150, "userFloorsAscendedGoal": 10, "minHeartRate": 45, "maxHeartRate": 95, "restingHeartRate": 48, "lastSevenDaysAvgRestingHeartRate": 50, "source": "GARMIN", "averageStressLevel": 26, "maxStressLevel": 87, "stressDuration": 42480, "restStressDuration": 42120, "activityStressDuration": 900, "uncategorizedStressDuration": 480, "totalStressDuration": 85980, "lowStressDuration": 35340, "mediumStressDuration": 6780, "highStressDuration": 360, "stressPercentage": 49.41, "restStressPercentage": 48.99, "activityStressPercentage": 1.05, "uncategorizedStressPercentage": 0.56, "lowStressPercentage": 41.1, "mediumStressPercentage": 7.89, "highStressPercentage": 0.42, "stressQualifier": "BALANCED", "measurableAwakeDuration": 54120, "measurableAsleepDuration": 31380, "lastSyncTimestampGMT": null, "minAvgHeartRate": 46, "maxAvgHeartRate": 91, "bodyBatteryChargedValue": 91, "bodyBatteryDrainedValue": 66, "bodyBatteryHighestValue": 95, "bodyBatteryLowestValue": 5, "bodyBatteryMostRecentValue": 30, "bodyBatteryDuringSleep": null, "bodyBatteryVersion": 3.0, "abnormalHeartRateAlertsCount": null, "averageSpo2": null, "lowestSpo2": null, "latestSpo2": null, "latestSpo2ReadingTimeGmt": null, "latestSpo2ReadingTimeLocal": null, "averageMonitoringEnvironmentAltitude": 450.0, "restingCaloriesFromActivity": null, "bodyBatteryDynamicFeedbackEvent": {"eventTimestampGmt": "2024-02-05T19:15:28", "bodyBatteryLevel": "HIGH", "feedbackShortType": "SLEEP_PREPARATION_RECOVERING_AND_INACTIVE", "feedbackLongType": "SLEEP_PREPARATION_RECOVERING_AND_INACTIVE"}, "endOfDayBodyBatteryDynamicFeedbackEvent": {"eventTimestampGmt": "2024-02-05T22:29:53", "bodyBatteryLevel": "HIGH", "feedbackShortType": "SLEEP_TIME_PASSED_RECOVERING_AND_INACTIVE", "feedbackLongType": "SLEEP_TIME_PASSED_RECOVERING_AND_INACTIVE"}, "bodyBatteryActivityEventList": [{"eventType": "SLEEP", "eventStartTimeGmt": "2024-02-04T21:18:00", "timezoneOffset": 3600000, "durationInMilliseconds": 37560000, "bodyBatteryImpact": 88, "feedbackType": "NONE", "shortFeedback": "NONE", "deviceId": 3446825437, "activityName": null, "activityType": null, "activityId": null, "eventUpdateTimeGmt": "2024-02-05T07:44:39"}], "avgWakingRespirationValue": 13.0, "highestRespirationValue": 16.0, "lowestRespirationValue": 8.0, "latestRespirationValue": 14.0, "latestRespirationTimeGMT": "2024-02-05T23:00:00.0"}