{"userProfileId": 116219307, "totalKilocalories": 2742.0, "activeKilocalories": 866.0, "bmrKilocalories": 1876.0, "wellnessKilocalories": 2742.0, "burnedKilocalories": null, "consumedKilocalories": null, "remainingKilocalories": 2742.0, "totalSteps": 14413, "netCalorieGoal": null, "totalDistanceMeters": 15422, "wellnessDistanceMeters": 11568, "wellnessActiveKilocalories": 866.0, "netRemainingKilocalories": 866.0, "userDailySummaryId": 116219307, "calendarDate": "2024-02-14", "rule": {"typeId": 2, "typeKey": "private"}, "uuid": "4685a6f39ba54a37a5820d89d2e06a13", "dailyStepGoal": 10000, "wellnessStartTimeGmt": "2024-02-13T23:00:00.0", "wellnessStartTimeLocal": "2024-02-14T00:00:00.0", "wellnessEndTimeGmt": "2024-02-14T23:00:00.0", "wellnessEndTimeLocal": "2024-02-15T00:00:00.0", "durationInMilliseconds": 86400000, "wellnessDescription": null, "highlyActiveSeconds": 4865, "activeSeconds": 3163, "sedentarySeconds": 49332, "sleepingSeconds": 29040, "includesWellnessData": true, "includesActivityData": true, "includesCalorieConsumedData": false, "privacyProtected": false, "moderateIntensityMinutes": 35, "vigorousIntensityMinutes": 72, "floorsAscendedInMeters": 195.072, "floorsDescendedInMeters": 151.97, "floorsAscended": 64.0, "floorsDescended": 49.85892, "intensityMinutesGoal": 150, "userFloorsAscendedGoal": 10, "minHeartRate": 46, "maxHeartRate": 156, "restingHeartRate": 49, "lastSevenDaysAvgRestingHeartRate": 49, "source": "GARMIN", "averageStressLevel": 27, "maxStressLevel": 94, "stressDuration": 28920, "restStressDuration": 36180, "activityStressDuration": 9840, "uncategorizedStressDuration": 10320, "totalStressDuration": 85260, "lowStressDuration": 18360, "mediumStressDuration": 10200, "highStressDuration": 360, "stressPercentage": 33.92, "restStressPercentage": 42.43, "activityStressPercentage": 11.54, "uncategorizedStressPercentage": 12.1, "lowStressPercentage": 21.53, "mediumStressPercentage": 11.96, "highStressPercentage": 0.42, "stressQualifier": "BALANCED", "measurableAwakeDuration": 46800, "measurableAsleepDuration": 28140, "lastSyncTimestampGMT": null, "minAvgHeartRate": 47, "maxAvgHeartRate": 154, "bodyBatteryChargedValue": 80, "bodyBatteryDrainedValue": 79, "bodyBatteryHighestValue": 100, "bodyBatteryLowestValue": 23, "bodyBatteryMostRecentValue": 32, "bodyBatteryDuringSleep": 69, "bodyBatteryVersion": 3.0, "abnormalHeartRateAlertsCount": null, "averageSpo2": null, "lowestSpo2": null, "latestSpo2": null, "latestSpo2ReadingTimeGmt": null, "latestSpo2ReadingTimeLocal": null, "averageMonitoringEnvironmentAltitude": 443.0, "restingCaloriesFromActivity": 134.0, "bodyBatteryDynamicFeedbackEvent": {"eventTimestampGmt": "2024-02-14T21:28:12", "bodyBatteryLevel": "HIGH", "feedbackShortType": "SLEEP_PREPARATION_BALANCED_AND_INTENSIVE_EXERCISE", "feedbackLongType": "SLEEP_PREPARATION_BALANCED_AND_INTENSIVE_EXERCISE"}, "endOfDayBodyBatteryDynamicFeedbackEvent": {"eventTimestampGmt": "2024-02-14T22:30:03", "bodyBatteryLevel": "HIGH", "feedbackShortType": "SLEEP_TIME_PASSED_BALANCED_AND_INTENSIVE_EXERCISE", "feedbackLongType": "SLEEP_TIME_PASSED_BALANCED_AND_INTENSIVE_EXERCISE"}, "bodyBatteryActivityEventList": [{"eventType": "SLEEP", "eventStartTimeGmt": "2024-02-13T23:09:00", "timezoneOffset": 3600000, "durationInMilliseconds": 28140000, "bodyBatteryImpact": 69, "feedbackType": "NONE", "shortFeedback": "NONE", "deviceId": 3446825437, "activityName": null, "activityType": null, "activityId": null, "eventUpdateTimeGmt": "2024-02-14T06:58:18"}, {"eventType": "ACTIVITY", "eventStartTimeGmt": "2024-02-14T08:57:03", "timezoneOffset": 3600000, "durationInMilliseconds": 720000, "bodyBatteryImpact": -4, "feedbackType": "EXERCISE_TRAINING_EFFECT_BELOW_2", "shortFeedback": "EASY_RECOVERY", "deviceId": 3446825437, "activityName": "Zurich eBiking", "activityType": "e_bike_fitness", "activityId": 13955777962, "eventUpdateTimeGmt": "2024-02-14T09:09:51"}, {"eventType": "ACTIVITY", "eventStartTimeGmt": "2024-02-14T17:28:10", "timezoneOffset": 3600000, "durationInMilliseconds": 3120000, "bodyBatteryImpact": -6, "feedbackType": "EXERCISE_TRAINING_EFFECT_2", "shortFeedback": "MAINTAINING_AEROBIC_BASE", "deviceId": 3446825437, "activityName": "Zurich Running", "activityType": "running", "activityId": 13963180260, "eventUpdateTimeGmt": "2024-02-14T18:20:33"}, {"eventType": "ACTIVITY", "eventStartTimeGmt": "2024-02-14T18:43:40", "timezoneOffset": 3600000, "durationInMilliseconds": 1560000, "bodyBatteryImpact": -1, "feedbackType": "EXERCISE_TRAINING_EFFECT_BELOW_2", "shortFeedback": "EASY_AEROBIC_BASE", "deviceId": 3446825437, "activityName": null, "activityType": null, "activityId": null, "eventUpdateTimeGmt": "2024-02-14T19:10:18"}, {"eventType": "ACTIVITY", "eventStartTimeGmt": "2024-02-14T19:13:52", "timezoneOffset": 3600000, "durationInMilliseconds": 780000, "bodyBatteryImpact": -2, "feedbackType": "EXERCISE_TRAINING_EFFECT_BELOW_2", "shortFeedback": "EASY_RECOVERY", "deviceId": 3446825437, "activityName": null, "activityType": null, "activityId": null, "eventUpdateTimeGmt": "2024-02-14T19:26:54"}], "avgWakingRespirationValue": 13.0, "highestRespirationValue": 21.0, "lowestRespirationValue": 9.0, "latestRespirationValue": 11.0, "latestRespirationTimeGMT": "2024-02-14T23:00:00.0"}